docs/conf.py
joe_lab/__init__.py
joe_lab/initial_states.py
joe_lab/joe.py
joe_lab/models.py
joe_lab/sponge_layer.py
joe_lab/time_stepper.py
joe_lab/utils.py
joe_lab/visualization.py
joe_lab/demos/bbm.py
joe_lab/demos/gardner-bbm.py
joe_lab/demos/gardner_soliton_test.py
joe_lab/demos/kdv.py
joe_lab/demos/kdv_soliton_accuracy.py
joe_lab/demos/kdv_soliton_test.py
joe_lab/demos/kdv_soliton_turbulence.py
joe_lab/demos/kn_nullwave.py
joe_lab/demos/ks.py
joe_lab/demos/nls.py
joe_lab/demos/sinegordon.py
joe_lab/projects/bbm_sw_turbulence.py
joe_lab/projects/gardner-bbm_st.py
joe_lab/projects/gardner_soliton_turbulence.py
joe_lab/projects/phi4_radiation_damping.py
joe_lab/projects/phi4pert_accuracy.py
joe_lab-0.0.6.dist-info/LICENSE
joe_lab-0.0.6.dist-info/METADATA
joe_lab-0.0.6.dist-info/WHEEL
joe_lab-0.0.6.dist-info/top_level.txt
joe_lab-0.0.6.dist-info/RECORD
