Metadata-Version: 2.1
Name: joe_lab
Version: 0.0.6
Summary: A package for solving 1+1-dimensional PDEs quickly and accurately with Fourier spectral discretization in space and high-order time-stepping.
Author-email: Adam George Morgan <adam.morgan@mail.utoronto.ca>
Project-URL: Homepage, https://github.com/ageorgemorgan/joe
Project-URL: Issues, https://github.com/ageorgemorgan/joe/issues
Classifier: Programming Language :: Python :: 3
Classifier: License :: OSI Approved :: MIT License
Classifier: Operating System :: OS Independent
Requires-Python: >=3.8
License-File: LICENSE
Requires-Dist: alive-progress >=3.0.0
Requires-Dist: cmocean >=3.0.0
Requires-Dist: joblib >=1.2.0
Requires-Dist: numpy >=1.25.2
Requires-Dist: scipy >=1.10.0
Requires-Dist: jupyterlab
Requires-Dist: pytest
Provides-Extra: docs
Requires-Dist: myst-parser >=0.13 ; extra == 'docs'
Requires-Dist: sphinx >=4.0 ; extra == 'docs'
Requires-Dist: sphinx-copybutton ; extra == 'docs'
Requires-Dist: sphinx-autodoc-typehints ; extra == 'docs'
Requires-Dist: sphinx-rtd-theme ; extra == 'docs'
